praestans/__init__.py
praestans/bin.py
praestans/dec.py
praestans/err.py
praestans/hex.py
praestans/oct.py
praestans-0.1.2.dist-info/LICENSE
praestans-0.1.2.dist-info/METADATA
praestans-0.1.2.dist-info/WHEEL
praestans-0.1.2.dist-info/top_level.txt
praestans-0.1.2.dist-info/RECORD
