Metadata-Version: 2.1
Name: praestans
Version: 0.1.2
Summary: python module that enables easy conversions between number systems
Home-page: https://github.com/apotursun963/praestans
Author: Abdullah Tursun
Author-email: tursunapo333@gmail.com
Classifier: Programming Language :: Python :: 3
Classifier: License :: OSI Approved :: MIT License
Classifier: Operating System :: OS Independent
License-File: LICENSE
